{
  "logoType": "lucideIcon",
  "logo": {
    "lucideIcon": "cpu",
    "imagePath": "",
    "imageLink": ""
  },
  "logoScale": 1.2,
  "iconColorType": "default",
  "wordmark": "Elettrotecnica",
  "customFont": "interfaceFont",
  "fontSize": "4em",
  "fontColorType": "default",
  "fontWeight": 600,
  "maxResults": 5,
  "showStarredFiles": false,
  "showRecentFiles": true,
  "maxRecentFiles": 5,
  "storeRecentFile": true,
  "showPath": true,
  "selectionHighlight": "default",
  "showShortcuts": true,
  "markdownOnly": true,
  "unresolvedLinks": false,
  "recentFilesStore": [
    {
      "filepath": "old/circuiti elettrici/Bipoli notevoli.md",
      "timestamp": 1724401590021
    },
    {
      "filepath": "old/circuiti elettrici/Circuiti equivalenti.md",
      "timestamp": 1724401582737
    },
    {
      "filepath": "old/circuiti elettrici/Classificazione dei bipoli.md",
      "timestamp": 1724401574150
    },
    {
      "filepath": "old/circuiti elettrici/Connessione di bipoli.md",
      "timestamp": 1724401564848
    },
    {
      "filepath": "old/circuiti elettrici/Leggi per i circuiti.md",
      "timestamp": 1724401540468
    }
  ],
  "starredFileStore": [],
  "searchDelay": 0,
  "replaceNewTabs": true,
  "newTabOnStart": true,
  "closePreviousSessionTabs": true,
  "omnisearch": false
}